{
  "oraAggiornamento": "11/04, 06:46",
  "sezioni": {
    "pescara": {
      "color": "#005f73",
      "news": [
        {
          "titolo": "Pescara-Sampdoria: le strategie tattiche in vista del confronto",
          "articolo": "Il match tra Pescara e Sampdoria si preannuncia come un banco di prova significativo per entrambe le compagini, chiamate a consolidare i rispettivi assetti tattici in una fase cruciale del campionato. Sotto la guida tecnica di Attilio Lombardo, la formazione ospite punta a ritrovare solidità e concretezza in fase offensiva, cercando di sfruttare le incursioni sulle fasce per scardinare la retroguardia avversaria. Dalla parte opposta, il Pescara di mister Gorgone sta lavorando intensamente sul consolidamento della linea mediana, cercando di bilanciare la fase di interdizione con una manovra più fluida e propositiva. Le probabili formazioni indicano una volontà condivisa di non concedere spazi centrali, con i due tecnici orientati verso moduli che privilegiano il controllo del ritmo di gioco. Sarà fondamentale la gestione delle seconde palle e la reattività dei reparti arretrati, in un incontro dove ogni dettaglio tattico potrebbe determinare l'esito finale della sfida. I tifosi attendono con trepidazione il fischio d'inizio, consapevoli che la preparazione atletica e la precisione nei passaggi saranno gli elementi chiave per conquistare l'intera posta in palio.",
          "commento": "Che spettacolo vedere due squadre così determinate a darsi battaglia sul campo! È un momento di calcio fantastico che promette scintille e un'intensità agonistica davvero travolgente per tutti gli appassionati!",
          "categoria": "Calcio",
          "immagine": "sport_pescara.webp"
        },
        {
          "titolo": "Verso Pescara-Sampdoria: altri 1000 biglietti in vendita",
          "articolo": "Notizia battuta dalle agenzie: \"Verso Pescara-Sampdoria: altri 1000 biglietti in vendita\". L'Intelligenza Artificiale è in pausa caffè.",
          "commento": "Lo stagista ha rovesciato la genziana sul server del sito.",
          "categoria": "Calcio",
          "immagine": "sport_pescara.webp"
        },
        {
          "titolo": "Guida autonoma, Niulinx la sfida italiana ai robotaxi. Round da 38 milioni",
          "articolo": "Notizia battuta dalle agenzie: \"Guida autonoma, Niulinx la sfida italiana ai robotaxi. Round da 38 milioni\". L'Intelligenza Artificiale è in pausa caffè.",
          "commento": "Lo stagista ha rovesciato la genziana sul server del sito.",
          "categoria": "Futuro",
          "immagine": "ai_tech.webp"
        },
        {
          "titolo": "Mistero su: Il Ponte del Mare diventa uno scivolo acquatico",
          "articolo": "Avevamo in serbo uno scoop clamoroso su \"Il Ponte del Mare diventa uno scivolo acquatico\", ma un gabbiano ci ha rubato gli appunti.",
          "commento": "Notizia troppo assurda perfino per noi, ci asteniamo.",
          "categoria": "Satira",
          "immagine": "satira.webp",
          "is_satira": true
        },
        {
          "titolo": "Mistero su: Arrosticini sintetici stampati in 3D con carne di nuvola",
          "articolo": "Avevamo in serbo uno scoop clamoroso su \"Arrosticini sintetici stampati in 3D con carne di nuvola\", ma un gabbiano ci ha rubato gli appunti.",
          "commento": "Il Delfino è in sciopero per carenza di arrosticini.",
          "categoria": "Satira",
          "immagine": "satira.webp",
          "is_satira": true
        },
        {
          "titolo": "Mistero su: Alieni avvistati a bere birra a Pescara Vecchia",
          "articolo": "Avevamo in serbo uno scoop clamoroso su \"Alieni avvistati a bere birra a Pescara Vecchia\", ma un gabbiano ci ha rubato gli appunti.",
          "commento": "Lo stagista ha rovesciato la genziana sul server del sito.",
          "categoria": "Satira",
          "immagine": "satira.webp",
          "is_satira": true
        }
      ]
    },
    "mondo": {
      "color": "#0a9396",
      "news": [
        {
          "titolo": "Streaming: Prime Video davanti, Netflix tallona e Hbo Max entra in punta di piedi",
          "articolo": "Notizia battuta dalle agenzie: \"Streaming: Prime Video davanti, Netflix tallona e Hbo Max entra in punta di piedi\". L'Intelligenza Artificiale è in pausa caffè.",
          "commento": "Il Delfino è in sciopero per carenza di arrosticini.",
          "categoria": "Streaming",
          "immagine": "netflix.webp"
        },
        {
          "titolo": "Netflix Playground, la nuova app di Netflix dedicata agli utenti più piccoli",
          "articolo": "Notizia battuta dalle agenzie: \"Netflix Playground, la nuova app di Netflix dedicata agli utenti più piccoli\". L'Intelligenza Artificiale è in pausa caffè.",
          "commento": "La nostra Intelligenza Artificiale è andata a farsi il bagno a Pescara Vecchia.",
          "categoria": "Streaming",
          "immagine": "netflix.webp"
        },
        {
          "titolo": "Overtourism per la fioritura dei ciliegi in Giappone, annullato un famoso festival",
          "articolo": "Notizia battuta dalle agenzie: \"Overtourism per la fioritura dei ciliegi in Giappone, annullato un famoso festival\". L'Intelligenza Artificiale è in pausa caffè.",
          "commento": "Il Delfino è in sciopero per carenza di arrosticini.",
          "categoria": "Esteri",
          "immagine": "giappone.webp"
        },
        {
          "titolo": "Mistero su: Il porto di Pescara dichiarato zona extraterrestre",
          "articolo": "Avevamo in serbo uno scoop clamoroso su \"Il porto di Pescara dichiarato zona extraterrestre\", ma un gabbiano ci ha rubato gli appunti.",
          "commento": "Lo stagista ha rovesciato la genziana sul server del sito.",
          "categoria": "Satira",
          "immagine": "satira_mondo.webp",
          "is_satira": true
        },
        {
          "titolo": "Mistero su: La Nave di Cascella prende il largo per una crociera ai Caraibi",
          "articolo": "Avevamo in serbo uno scoop clamoroso su \"La Nave di Cascella prende il largo per una crociera ai Caraibi\", ma un gabbiano ci ha rubato gli appunti.",
          "commento": "Il Delfino è in sciopero per carenza di arrosticini.",
          "categoria": "Satira",
          "immagine": "satira_mondo.webp",
          "is_satira": true
        }
      ]
    }
  }
}